llama_bsl.py
llama_bsl-0.5.dist-info/LICENSE.md
llama_bsl-0.5.dist-info/METADATA
llama_bsl-0.5.dist-info/WHEEL
llama_bsl-0.5.dist-info/entry_points.txt
llama_bsl-0.5.dist-info/top_level.txt
llama_bsl-0.5.dist-info/RECORD
