Metadata-Version: 2.1
Name: llama-bsl
Version: 0.5
Summary: Script to communicate with Texas Instruments CC13xx/CC2538/CC26xx Serial Boot Loader (Fork of cc2538-bsl.py)
Home-page: https://github.com/electrolama/llama-bsl
Author: Omer Kilic
Author-email: omerkilic@gmail.com
License: BSD-3-Clause
Keywords: cc2538,cc1310,cc13xx,bootloader,cc26xx,cc2650,cc2640
Platform: posix
Classifier: Development Status :: 4 - Beta
Classifier: Environment :: Console
Classifier: Intended Audience :: Developers
Classifier: License :: OSI Approved :: BSD License
Classifier: Operating System :: POSIX :: Linux
Classifier: Operating System :: MacOS
Classifier: Operating System :: Microsoft :: Windows
Classifier: Programming Language :: Python :: 3
Classifier: Topic :: Scientific/Engineering
Requires-Python: >=3.4
License-File: LICENSE.md
Requires-Dist: pip (>=10)
Requires-Dist: setuptools
Requires-Dist: wheel
Requires-Dist: pyserial (==3.5)
Requires-Dist: intelhex (==2.3.0)
Requires-Dist: requests (==2.26.0)
